jiveplot/__init__.py
jiveplot/command.py
jiveplot/enumerations.py
jiveplot/functional.py
jiveplot/gencolors.py
jiveplot/helpfile.py
jiveplot/hvutil.py
jiveplot/jenums.py
jiveplot/jplotter.py
jiveplot/label_v6.py
jiveplot/ms2mappings.py
jiveplot/ms2util.py
jiveplot/parsers.py
jiveplot/plotiterator.py
jiveplot/plots.py
jiveplot/plotutil.py
jiveplot/selection.py
jiveplot/semanticversion.py
jiveplot/postprocessing/__init__.py
jiveplot/postprocessing/compare_data.py
jiveplot/postprocessing/mypp.py
jiveplot/postprocessing/phatime.py
jiveplot-2.1.0.data/scripts/jplotter
jiveplot-2.1.0.data/scripts/klk1
jiveplot-2.1.0.data/scripts/standardplots
jiveplot-2.1.0.dist-info/licenses/LICENSE
jiveplot-2.1.0.dist-info/METADATA
jiveplot-2.1.0.dist-info/WHEEL
jiveplot-2.1.0.dist-info/top_level.txt
jiveplot-2.1.0.dist-info/RECORD
