Metadata-Version: 2.4
Name: jiveplot
Version: 2.1.0
Summary: Python based visualization tool for AIPS++/CASA MeasurementSet version 2 data
Author-email: Marjolein Verkouter <verkouter@jive.eu>
License: GPL-3.0
Project-URL: Homepage, https://github.com/haavee/jiveplot
Keywords: astronomy,astrophysics,VLBI
Classifier: Intended Audience :: Developers
Classifier: Intended Audience :: Science/Research
Classifier: License :: OSI Approved :: GNU General Public License v3 (GPLv3)
Classifier: Operating System :: OS Independent
Classifier: Programming Language :: Python :: 3
Classifier: Programming Language :: Python :: 3 :: Only
Classifier: Programming Language :: Python :: 3.8
Classifier: Programming Language :: Python :: 3.9
Classifier: Programming Language :: Python :: 3.10
Classifier: Programming Language :: Python :: 3.11
Classifier: Programming Language :: Python :: 3.12
Classifier: Topic :: Scientific/Engineering :: Astronomy
Requires-Python: >=3.8
License-File: LICENSE
Requires-Dist: numpy
Requires-Dist: python-casacore
Requires-Dist: python-pgplot
Requires-Dist: six
Dynamic: license-file
